process_file/__init__.py
process_file/package.py
process_file-0.4.0.dist-info/METADATA
process_file-0.4.0.dist-info/WHEEL
process_file-0.4.0.dist-info/top_level.txt
process_file-0.4.0.dist-info/RECORD
